babbage/__init__.py
babbage/api.py
babbage/cube.py
babbage/exc.py
babbage/manager.py
babbage/util.py
babbage/validation.py
babbage/version.py
babbage/model/__init__.py
babbage/model/aggregate.py
babbage/model/attribute.py
babbage/model/binding.py
babbage/model/concept.py
babbage/model/dimension.py
babbage/model/hierarchy.py
babbage/model/measure.py
babbage/model/model.py
babbage/query/__init__.py
babbage/query/aggregates.py
babbage/query/cuts.py
babbage/query/drilldowns.py
babbage/query/fields.py
babbage/query/ordering.py
babbage/query/pagination.py
babbage/query/parser.py
babbage/schema/model.json
babbage/schema/parser.ebnf
babbage-0.4.0.dist-info/LICENSE
babbage-0.4.0.dist-info/METADATA
babbage-0.4.0.dist-info/WHEEL
babbage-0.4.0.dist-info/namespace_packages.txt
babbage-0.4.0.dist-info/top_level.txt
babbage-0.4.0.dist-info/RECORD
