Metadata-Version: 2.1
Name: babbage
Version: 0.4.0
Summary: A light-weight analytical engine for OLAP processing
Home-page: http://github.com/openspending/babbage
Author: Friedrich Lindenberg
Author-email: friedrich@pudo.org
License: MIT
Keywords: sql sqlalchemy olap cubes analytics
Platform: UNKNOWN
Classifier: Development Status :: 3 - Alpha
Classifier: Intended Audience :: Developers
Classifier: License :: OSI Approved :: MIT License
Classifier: Operating System :: OS Independent
Classifier: Programming Language :: Python :: 2.7
Classifier: Programming Language :: Python :: 3.4
Classifier: Programming Language :: Python :: 3.5
Classifier: Programming Language :: Python :: 3.6
Requires-Dist: normality (>=0.2.2)
Requires-Dist: PyYAML (>=3.10)
Requires-Dist: six (>=1.7.3)
Requires-Dist: flask (>=0.10.1)
Requires-Dist: jsonschema (>=2.5.1)
Requires-Dist: sqlalchemy (>=1.0)
Requires-Dist: psycopg2 (>=2.6)
Requires-Dist: grako (==3.10.1)
